probpeaks/__init__.py
probpeaks/channel.py
probpeaks-0.0.1.dist-info/LICENSE
probpeaks-0.0.1.dist-info/METADATA
probpeaks-0.0.1.dist-info/WHEEL
probpeaks-0.0.1.dist-info/top_level.txt
probpeaks-0.0.1.dist-info/RECORD
