Metadata-Version: 2.1
Name: probpeaks
Version: 0.0.1
Summary: Time Series Peak Detection
Home-page: https://github.com/jon-chun/probpeaks
Author: Jon Chun
Author-email: jonchun@outlook.com
License: UNKNOWN
Project-URL: Bug Tracker, https://github.com/jon-chun/probpeaks/issues
Platform: UNKNOWN
Classifier: Programming Language :: Python :: 3
Classifier: License :: OSI Approved :: MIT License
Classifier: Operating System :: OS Independent
Requires-Python: >=3.6
License-File: LICENSE
